geetest_django/__init__.py
geetest_django/forms.py
geetest_django/utils.py
geetest_django/views.py
geetest_django-0.0.1.dist-info/DESCRIPTION.rst
geetest_django-0.0.1.dist-info/METADATA
geetest_django-0.0.1.dist-info/RECORD
geetest_django-0.0.1.dist-info/WHEEL
geetest_django-0.0.1.dist-info/metadata.json
geetest_django-0.0.1.dist-info/top_level.txt
