Metadata-Version: 1.0
Name: geetest-django
Version: 0.0.1
Summary: A session-based geetest api implementation
Home-page: https://github.com/winkidney/geetest-django
Author: winkidney
Author-email: winkidney@gmail.com
License: MIT
Platform: UNKNOWN
